MANIFEST.in
setup.py
fabric_recipes.egg-info/PKG-INFO
fabric_recipes.egg-info/SOURCES.txt
fabric_recipes.egg-info/dependency_links.txt
fabric_recipes.egg-info/requires.txt
fabric_recipes.egg-info/top_level.txt
recipes/__init__.py
recipes/django.py
recipes/functions.py
recipes/gunicorn.py
recipes/nginx.py
recipes/project.py
recipes/utils.py
recipes/scripts/__init__.py
recipes/scripts/__init__.pyc
recipes/scripts/gunicorn_project.conf
recipes/scripts/nginx_server.conf
recipes/scripts/nginx_site.conf