Metadata-Version: 1.0
Name: fabric-recipes
Version: 0.3.1
Summary: quick solution to perform deploy a Django app using nginx and gunicorn
Home-page: https://github.com/petry/fabric-recipes/
Author: Marcos Daniel Petry
Author-email: marcospetry@gmail.com
License: BSD
Keywords: fabric django gunicorn deploy
Platform: UNKNOWN
Classifier: Development Status :: 3 - Alpha
Classifier: Topic :: Utilities
Classifier: License :: OSI Approved :: BSD License
